localstack/config.py
localstack/constants.py
localstack/deprecations.py
localstack/openapi.yaml
localstack/plugins.py
localstack/py.typed
localstack/version.py
localstack/aws/__init__.py
localstack/aws/accounts.py
localstack/aws/app.py
localstack/aws/chain.py
localstack/aws/client.py
localstack/aws/components.py
localstack/aws/connect.py
localstack/aws/forwarder.py
localstack/aws/gateway.py
localstack/aws/mocking.py
localstack/aws/patches.py
localstack/aws/scaffold.py
localstack/aws/skeleton.py
localstack/aws/spec-patches.json
localstack/aws/spec.py
localstack/aws/api/__init__.py
localstack/aws/api/core.py
localstack/aws/api/acm/__init__.py
localstack/aws/api/apigateway/__init__.py
localstack/aws/api/cloudcontrol/__init__.py
localstack/aws/api/cloudformation/__init__.py
localstack/aws/api/cloudwatch/__init__.py
localstack/aws/api/config/__init__.py
localstack/aws/api/dynamodb/__init__.py
localstack/aws/api/dynamodbstreams/__init__.py
localstack/aws/api/ec2/__init__.py
localstack/aws/api/es/__init__.py
localstack/aws/api/events/__init__.py
localstack/aws/api/firehose/__init__.py
localstack/aws/api/iam/__init__.py
localstack/aws/api/kinesis/__init__.py
localstack/aws/api/kms/__init__.py
localstack/aws/api/lambda_/__init__.py
localstack/aws/api/logs/__init__.py
localstack/aws/api/opensearch/__init__.py
localstack/aws/api/pipes/__init__.py
localstack/aws/api/redshift/__init__.py
localstack/aws/api/resource_groups/__init__.py
localstack/aws/api/resourcegroupstaggingapi/__init__.py
localstack/aws/api/route53/__init__.py
localstack/aws/api/route53resolver/__init__.py
localstack/aws/api/s3/__init__.py
localstack/aws/api/s3control/__init__.py
localstack/aws/api/scheduler/__init__.py
localstack/aws/api/secretsmanager/__init__.py
localstack/aws/api/ses/__init__.py
localstack/aws/api/sns/__init__.py
localstack/aws/api/sqs/__init__.py
localstack/aws/api/ssm/__init__.py
localstack/aws/api/stepfunctions/__init__.py
localstack/aws/api/sts/__init__.py
localstack_core-4.9.1.dist-info/licenses/LICENSE.txt
localstack_core-4.9.1.dist-info/METADATA
localstack_core-4.9.1.dist-info/WHEEL
localstack_core-4.9.1.dist-info/entry_points.txt
localstack_core-4.9.1.dist-info/plux.json
localstack_core-4.9.1.dist-info/top_level.txt
localstack_core-4.9.1.dist-info/RECORD
